Metadata-Version: 2.4
Name: iflow-mcp_python-mcp-server-client
Version: 0.1.0
Summary: MCP服务器，用于搜索技术文档，支持langchain、llama-index、autogen等多个库
Requires-Python: >=3.11
Requires-Dist: bs4>=0.0.2
Requires-Dist: httpx>=0.28.1
Requires-Dist: mcp[cli]>=1.4.1
Requires-Dist: openai>=1.66.3
Requires-Dist: python-dotenv>=1.0.0
